{
  "remarks" : [ ],
  "links" : [ {
    "href" : "http://rdap.labs.lacnic.net/autnum/17147",
    "rel" : "self",
    "value" : "http://rdap.labs.lacnic.net/autnum/17147"
  } ],
  "entities" : [ {
    "remarks" : [ ],
    "links" : [ {
      "href" : "http://rdap.labs.lacnic.net/entity/CL-GOCH1-LACNIC",
      "rel" : "self",
      "value" : "http://rdap.labs.lacnic.net/entity/CL-GOCH1-LACNIC"
    } ],
    "vcardArray" : ["vcard",[["version",{},"text","4.0"],["fn",{},"text","Jefa de Division TI / M. Interior Chile"],["adr",{"label":"Palacio de la Moneda, oficina 201 S/N ()\nSantiago, RM 8340687\nCL","type":"work"},"text",["","","Palacio de la Moneda, oficina 201 S/N ()","Santiago","RM","8340687","CL"]],["email",{"type":"work"},"text","nic@INTERIOR.GOV.CL"],["tel",{"type":"work"},"text","56 2 6904192 ()"],["org",{},"text",["Ministerio del Interior y de Seguridad Publica - Gobierno de Chile"]],["kind",{},"text","individual"]] ],
    "roles" : [ "registrant" ],
    "entities" : [ {
      "remarks" : [ ],
      "links" : [ {
        "href" : "http://rdap.labs.lacnic.net/entity/TMC",
        "rel" : "self",
        "value" : "http://rdap.labs.lacnic.net/entity/TMC"
      } ],
      "vcardArray" : ["vcard",[["version",{},"text","4.0"],["fn",{},"text","Jefa de Division TI / M. Interior Chile"],["adr",{"label":"Palacio de la Moneda S/N (Of. 201)\nSantiago, RM 8340687\nCL","type":"work"},"text",["","","Palacio de la Moneda S/N (Of. 201)","Santiago","RM","8340687","CL"]],["email",{"type":"work"},"text","nic@INTERIOR.GOV.CL"],["tel",{"type":"work"},"text","56 2 26904192 ()"],["kind",{},"text","individual"],["lang",{"pref":"1"},"language-tag","EN"]] ],
      "roles" : [ "administrative" ],
      "entities" : [ ],
      "events" : [ {
        "eventAction" : "registration",
        "eventDate" : "20040810",
        "eventActor" : null
      }, {
        "eventAction" : "last changed",
        "eventDate" : "20140529",
        "eventActor" : "TMC"
      } ],
      "handle" : "TMC"
    } ],
    "events" : [ {
      "eventAction" : "registration",
      "eventDate" : "20110810",
      "eventActor" : null
    }, {
      "eventAction" : "last changed",
      "eventDate" : "20140529",
      "eventActor" : "TMC"
    } ],
    "handle" : "CL-GOCH1-LACNIC"
  }, {
    "remarks" : [ ],
    "links" : [ {
      "href" : "http://rdap.labs.lacnic.net/entity/TMC",
      "rel" : "self",
      "value" : "http://rdap.labs.lacnic.net/entity/TMC"
    } ],
    "vcardArray" : ["vcard",[["version",{},"text","4.0"],["fn",{},"text","Jefa de Division TI / M. Interior Chile"],["adr",{"label":"Palacio de la Moneda S/N (Of. 201)\nSantiago, RM 8340687\nCL","type":"work"},"text",["","","Palacio de la Moneda S/N (Of. 201)","Santiago","RM","8340687","CL"]],["email",{"type":"work"},"text","nic@INTERIOR.GOV.CL"],["tel",{"type":"work"},"text","56 2 26904192 ()"],["kind",{},"text","individual"],["lang",{"pref":"1"},"language-tag","EN"]] ],
    "roles" : [ "tech" ],
    "entities" : [ ],
    "events" : [ {
      "eventAction" : "registration",
      "eventDate" : "20040810",
      "eventActor" : null
    }, {
      "eventAction" : "last changed",
      "eventDate" : "20140529",
      "eventActor" : "TMC"
    } ],
    "handle" : "TMC"
  }, {
    "remarks" : [ ],
    "links" : [ {
      "href" : "http://rdap.labs.lacnic.net/entity/TMC",
      "rel" : "self",
      "value" : "http://rdap.labs.lacnic.net/entity/TMC"
    } ],
    "vcardArray" : ["vcard",[["version",{},"text","4.0"],["fn",{},"text","Jefa de Division TI / M. Interior Chile"],["adr",{"label":"Palacio de la Moneda S/N (Of. 201)\nSantiago, RM 8340687\nCL","type":"work"},"text",["","","Palacio de la Moneda S/N (Of. 201)","Santiago","RM","8340687","CL"]],["email",{"type":"work"},"text","nic@INTERIOR.GOV.CL"],["tel",{"type":"work"},"text","56 2 26904192 ()"],["kind",{},"text","individual"],["lang",{"pref":"1"},"language-tag","EN"]] ],
    "roles" : [ "abuse" ],
    "entities" : [ ],
    "events" : [ {
      "eventAction" : "registration",
      "eventDate" : "20040810",
      "eventActor" : null
    }, {
      "eventAction" : "last changed",
      "eventDate" : "20140529",
      "eventActor" : "TMC"
    } ],
    "handle" : "TMC"
  } ],
  "startAutnum" : 17147,
  "endAutnum" : 17147,
  "status" : [ "allocated" ],
  "events" : [ {
    "eventAction" : "registration",
    "eventDate" : "20000731",
    "eventActor" : null
  }, {
    "eventAction" : "last changed",
    "eventDate" : "20040517",
    "eventActor" : "TMC"
  } ],
  "type" : null,
  "handle" : "17147-LACNIC",
  "country" : "CL"
}