{
  "startAutnum" : 21741,
  "endAutnum" : 21741,
  "status" : [ "allocated" ],
  "remarks" : [ ],
  "links" : [ {
    "rel" : "self",
    "href" : "http://rdap.labs.lacnic.net/autnum/21741",
    "value" : "http://rdap.labs.lacnic.net/autnum/21741"
  } ],
  "events" : [ {
    "eventAction" : "registration",
    "eventDate" : "20010618",
    "eventActor" : null
  }, {
    "eventAction" : "last changed",
    "eventDate" : "20130306",
    "eventActor" : "ATS25"
  } ],
  "entities" : [ {
    "roles" : [ "registrant" ],
    "remarks" : [ ],
    "links" : [ {
      "rel" : "self",
      "href" : "http://rdap.labs.lacnic.net/entity/BR-VIHO-LACNIC",
      "value" : "http://rdap.labs.lacnic.net/entity/BR-VIHO-LACNIC"
    } ],
    "vcardArray" : ["vcard",[["version",{},"text","4.0"],["fn",{},"text","Andre Trujillo da Silva"],["adr",{"label":"Av. das Na??es Unidas 11541 (7? andar)\nS?o Paulo, SP 04578-000\nBR","type":"work"},"text",["","","Av. das Na??es Unidas 11541 (7? andar)","S?o Paulo","SP","04578-000","BR"]],["email",{"type":"work"},"text","ATS25@NUMERACAO.REGISTRO.BR"],["tel",{"type":"work"},"text","55 11 55093511 ()"],["org",{},"text",["Visualcorp Holding"]],["kind",{},"text","individual"]] ],
    "events" : [ {
      "eventAction" : "registration",
      "eventDate" : "20130306",
      "eventActor" : null
    }, {
      "eventAction" : "last changed",
      "eventDate" : "20130308",
      "eventActor" : "ATS25"
    } ],
    "entities" : [ {
      "roles" : [ "administrative" ],
      "remarks" : [ ],
      "links" : [ {
        "rel" : "self",
        "href" : "http://rdap.labs.lacnic.net/entity/ATS25",
        "value" : "http://rdap.labs.lacnic.net/entity/ATS25"
      } ],
      "vcardArray" : ["vcard",[["version",{},"text","4.0"],["fn",{},"text","Andre Trujillo da Silva"],["adr",{"label":"Av. das Na??es Unidas 11541 (7? andar)\nS?o Paulo, SP 04578-000\nBR","type":"work"},"text",["","","Av. das Na??es Unidas 11541 (7? andar)","S?o Paulo","SP","04578-000","BR"]],["email",{"type":"work"},"text","ATS25@NUMERACAO.REGISTRO.BR"],["tel",{"type":"work"},"text","55 11 55093511 ()"],["kind",{},"text","individual"],["lang",{"pref":"1"},"language-tag","EN"]] ],
      "events" : [ {
        "eventAction" : "registration",
        "eventDate" : "20130306",
        "eventActor" : null
      }, {
        "eventAction" : "last changed",
        "eventDate" : "20130308",
        "eventActor" : "ATS25"
      } ],
      "entities" : [ ],
      "handle" : "ATS25"
    } ],
    "handle" : "BR-VIHO-LACNIC"
  }, {
    "roles" : [ "tech" ],
    "remarks" : [ ],
    "links" : [ {
      "rel" : "self",
      "href" : "http://rdap.labs.lacnic.net/entity/ATS25",
      "value" : "http://rdap.labs.lacnic.net/entity/ATS25"
    } ],
    "vcardArray" : ["vcard",[["version",{},"text","4.0"],["fn",{},"text","Andre Trujillo da Silva"],["adr",{"label":"Av. das Na??es Unidas 11541 (7? andar)\nS?o Paulo, SP 04578-000\nBR","type":"work"},"text",["","","Av. das Na??es Unidas 11541 (7? andar)","S?o Paulo","SP","04578-000","BR"]],["email",{"type":"work"},"text","ATS25@NUMERACAO.REGISTRO.BR"],["tel",{"type":"work"},"text","55 11 55093511 ()"],["kind",{},"text","individual"],["lang",{"pref":"1"},"language-tag","EN"]] ],
    "events" : [ {
      "eventAction" : "registration",
      "eventDate" : "20130306",
      "eventActor" : null
    }, {
      "eventAction" : "last changed",
      "eventDate" : "20130308",
      "eventActor" : "ATS25"
    } ],
    "entities" : [ ],
    "handle" : "ATS25"
  }, {
    "roles" : [ "abuse" ],
    "remarks" : [ ],
    "links" : [ {
      "rel" : "self",
      "href" : "http://rdap.labs.lacnic.net/entity/ATS25",
      "value" : "http://rdap.labs.lacnic.net/entity/ATS25"
    } ],
    "vcardArray" : ["vcard",[["version",{},"text","4.0"],["fn",{},"text","Andre Trujillo da Silva"],["adr",{"label":"Av. das Na??es Unidas 11541 (7? andar)\nS?o Paulo, SP 04578-000\nBR","type":"work"},"text",["","","Av. das Na??es Unidas 11541 (7? andar)","S?o Paulo","SP","04578-000","BR"]],["email",{"type":"work"},"text","ATS25@NUMERACAO.REGISTRO.BR"],["tel",{"type":"work"},"text","55 11 55093511 ()"],["kind",{},"text","individual"],["lang",{"pref":"1"},"language-tag","EN"]] ],
    "events" : [ {
      "eventAction" : "registration",
      "eventDate" : "20130306",
      "eventActor" : null
    }, {
      "eventAction" : "last changed",
      "eventDate" : "20130308",
      "eventActor" : "ATS25"
    } ],
    "entities" : [ ],
    "handle" : "ATS25"
  } ],
  "type" : null,
  "handle" : "21741-LACNIC",
  "country" : "BR"
}