{
  "startAutnum" : 263098,
  "endAutnum" : 263098,
  "status" : [ "allocated" ],
  "remarks" : [ ],
  "links" : [ {
    "rel" : "self",
    "href" : "http://rdap.labs.lacnic.net/autnum/263098",
    "value" : "http://rdap.labs.lacnic.net/autnum/263098"
  } ],
  "events" : [ {
    "eventAction" : "registration",
    "eventDate" : "20120426",
    "eventActor" : null
  }, {
    "eventAction" : "last changed",
    "eventDate" : "20130306",
    "eventActor" : "GCJ3"
  } ],
  "entities" : [ {
    "roles" : [ "registrant" ],
    "remarks" : [ ],
    "links" : [ {
      "rel" : "self",
      "href" : "http://rdap.labs.lacnic.net/entity/BR-ENSI1-LACNIC",
      "value" : "http://rdap.labs.lacnic.net/entity/BR-ENSI1-LACNIC"
    } ],
    "vcardArray" : ["vcard",[["version",{},"text","4.0"],["fn",{},"text","Amilton de Lucca"],["adr",{"label":"Av. das Na??es Unidas 11541 (7? andar)\nManaus, AM 04578-000\nBR","type":"work"},"text",["","","Av. das Na??es Unidas 11541 (7? andar)","Manaus","AM","04578-000","BR"]],["email",{"type":"work"},"text","AML23@NUMERACAO.REGISTRO.BR"],["tel",{"type":"work"},"text","55 92 55093511 ()"],["org",{},"text",["Eyes Nwhere Sistemas Inteligentes de Imagem Ltda"]],["kind",{},"text","individual"]] ],
    "events" : [ {
      "eventAction" : "registration",
      "eventDate" : "20130306",
      "eventActor" : null
    }, {
      "eventAction" : "last changed",
      "eventDate" : "20130307",
      "eventActor" : "AML23"
    } ],
    "entities" : [ {
      "roles" : [ "administrative" ],
      "remarks" : [ ],
      "links" : [ {
        "rel" : "self",
        "href" : "http://rdap.labs.lacnic.net/entity/AML23",
        "value" : "http://rdap.labs.lacnic.net/entity/AML23"
      } ],
      "vcardArray" : ["vcard",[["version",{},"text","4.0"],["fn",{},"text","Amilton de Lucca"],["adr",{"label":"Av. das Na??es Unidas 11541 (7? andar)\nS?o Paulo, SP 04578-000\nBR","type":"work"},"text",["","","Av. das Na??es Unidas 11541 (7? andar)","S?o Paulo","SP","04578-000","BR"]],["email",{"type":"work"},"text","AML23@NUMERACAO.REGISTRO.BR"],["tel",{"type":"work"},"text","55 11 55093511 ()"],["kind",{},"text","individual"],["lang",{"pref":"1"},"language-tag","EN"]] ],
      "events" : [ {
        "eventAction" : "registration",
        "eventDate" : "20130306",
        "eventActor" : null
      }, {
        "eventAction" : "last changed",
        "eventDate" : "20130308",
        "eventActor" : "AML23"
      } ],
      "entities" : [ ],
      "handle" : "AML23"
    } ],
    "handle" : "BR-ENSI1-LACNIC"
  }, {
    "roles" : [ "tech" ],
    "remarks" : [ ],
    "links" : [ {
      "rel" : "self",
      "href" : "http://rdap.labs.lacnic.net/entity/GCJ3",
      "value" : "http://rdap.labs.lacnic.net/entity/GCJ3"
    } ],
    "vcardArray" : ["vcard",[["version",{},"text","4.0"],["fn",{},"text","Gildo Castro da Silva J?nio"],["adr",{"label":"Av. das Na??es Unidas 11541 (7? andar)\nManaus, AM 04578-000\nBR","type":"work"},"text",["","","Av. das Na??es Unidas 11541 (7? andar)","Manaus","AM","04578-000","BR"]],["email",{"type":"work"},"text","GCJ3@NUMERACAO.REGISTRO.BR"],["tel",{"type":"work"},"text","55 92 55093511 ()"],["kind",{},"text","individual"],["lang",{"pref":"1"},"language-tag","EN"]] ],
    "events" : [ {
      "eventAction" : "registration",
      "eventDate" : "20130306",
      "eventActor" : null
    }, {
      "eventAction" : "last changed",
      "eventDate" : "20130308",
      "eventActor" : "GCJ3"
    } ],
    "entities" : [ ],
    "handle" : "GCJ3"
  }, {
    "roles" : [ "abuse" ],
    "remarks" : [ ],
    "links" : [ {
      "rel" : "self",
      "href" : "http://rdap.labs.lacnic.net/entity/GCJ3",
      "value" : "http://rdap.labs.lacnic.net/entity/GCJ3"
    } ],
    "vcardArray" : ["vcard",[["version",{},"text","4.0"],["fn",{},"text","Gildo Castro da Silva J?nio"],["adr",{"label":"Av. das Na??es Unidas 11541 (7? andar)\nManaus, AM 04578-000\nBR","type":"work"},"text",["","","Av. das Na??es Unidas 11541 (7? andar)","Manaus","AM","04578-000","BR"]],["email",{"type":"work"},"text","GCJ3@NUMERACAO.REGISTRO.BR"],["tel",{"type":"work"},"text","55 92 55093511 ()"],["kind",{},"text","individual"],["lang",{"pref":"1"},"language-tag","EN"]] ],
    "events" : [ {
      "eventAction" : "registration",
      "eventDate" : "20130306",
      "eventActor" : null
    }, {
      "eventAction" : "last changed",
      "eventDate" : "20130308",
      "eventActor" : "GCJ3"
    } ],
    "entities" : [ ],
    "handle" : "GCJ3"
  } ],
  "type" : null,
  "handle" : "263098-LACNIC",
  "country" : "BR"
}