{
  "startAutnum" : 263055,
  "endAutnum" : 263055,
  "status" : [ "allocated" ],
  "remarks" : [ ],
  "links" : [ {
    "rel" : "self",
    "href" : "http://rdap.labs.lacnic.net/autnum/263055",
    "value" : "http://rdap.labs.lacnic.net/autnum/263055"
  } ],
  "events" : [ {
    "eventAction" : "registration",
    "eventDate" : "20120315",
    "eventActor" : null
  }, {
    "eventAction" : "last changed",
    "eventDate" : "20130306",
    "eventActor" : "PTL8"
  } ],
  "entities" : [ {
    "roles" : [ "registrant" ],
    "remarks" : [ ],
    "links" : [ {
      "rel" : "self",
      "href" : "http://rdap.labs.lacnic.net/entity/BR-PTCS-LACNIC",
      "value" : "http://rdap.labs.lacnic.net/entity/BR-PTCS-LACNIC"
    } ],
    "vcardArray" : ["vcard",[["version",{},"text","4.0"],["fn",{},"text","PINHAIS TELECOM COMERCIO E SERVI?OS LTDA"],["adr",{"label":"Av. das Na??es Unidas 11541 (7? andar)\nPinhais, PR 04578-000\nBR","type":"work"},"text",["","","Av. das Na??es Unidas 11541 (7? andar)","Pinhais","PR","04578-000","BR"]],["email",{"type":"work"},"text","PTL8@NUMERACAO.REGISTRO.BR"],["tel",{"type":"work"},"text","55 41 55093511 ()"],["org",{},"text",["PINHAIS TELECOM COMERCIO E SERVI?OS LTDA"]],["kind",{},"text","individual"]] ],
    "events" : [ {
      "eventAction" : "registration",
      "eventDate" : "20130306",
      "eventActor" : null
    }, {
      "eventAction" : "last changed",
      "eventDate" : "20130307",
      "eventActor" : "PTL8"
    } ],
    "entities" : [ {
      "roles" : [ "administrative" ],
      "remarks" : [ ],
      "links" : [ {
        "rel" : "self",
        "href" : "http://rdap.labs.lacnic.net/entity/PTL8",
        "value" : "http://rdap.labs.lacnic.net/entity/PTL8"
      } ],
      "vcardArray" : ["vcard",[["version",{},"text","4.0"],["fn",{},"text","PINHAIS TELECOM COMERCIO E SERVI?OS LTDA"],["adr",{"label":"Av. das Na??es Unidas 11541 (7? andar)\nPinhais, PR 04578-000\nBR","type":"work"},"text",["","","Av. das Na??es Unidas 11541 (7? andar)","Pinhais","PR","04578-000","BR"]],["email",{"type":"work"},"text","PTL8@NUMERACAO.REGISTRO.BR"],["tel",{"type":"work"},"text","55 41 55093511 ()"],["kind",{},"text","individual"],["lang",{"pref":"1"},"language-tag","EN"]] ],
      "events" : [ {
        "eventAction" : "registration",
        "eventDate" : "20130306",
        "eventActor" : null
      }, {
        "eventAction" : "last changed",
        "eventDate" : "20130308",
        "eventActor" : "PTL8"
      } ],
      "entities" : [ ],
      "handle" : "PTL8"
    } ],
    "handle" : "BR-PTCS-LACNIC"
  }, {
    "roles" : [ "tech" ],
    "remarks" : [ ],
    "links" : [ {
      "rel" : "self",
      "href" : "http://rdap.labs.lacnic.net/entity/PTL8",
      "value" : "http://rdap.labs.lacnic.net/entity/PTL8"
    } ],
    "vcardArray" : ["vcard",[["version",{},"text","4.0"],["fn",{},"text","PINHAIS TELECOM COMERCIO E SERVI?OS LTDA"],["adr",{"label":"Av. das Na??es Unidas 11541 (7? andar)\nPinhais, PR 04578-000\nBR","type":"work"},"text",["","","Av. das Na??es Unidas 11541 (7? andar)","Pinhais","PR","04578-000","BR"]],["email",{"type":"work"},"text","PTL8@NUMERACAO.REGISTRO.BR"],["tel",{"type":"work"},"text","55 41 55093511 ()"],["kind",{},"text","individual"],["lang",{"pref":"1"},"language-tag","EN"]] ],
    "events" : [ {
      "eventAction" : "registration",
      "eventDate" : "20130306",
      "eventActor" : null
    }, {
      "eventAction" : "last changed",
      "eventDate" : "20130308",
      "eventActor" : "PTL8"
    } ],
    "entities" : [ ],
    "handle" : "PTL8"
  }, {
    "roles" : [ "abuse" ],
    "remarks" : [ ],
    "links" : [ {
      "rel" : "self",
      "href" : "http://rdap.labs.lacnic.net/entity/PTL8",
      "value" : "http://rdap.labs.lacnic.net/entity/PTL8"
    } ],
    "vcardArray" : ["vcard",[["version",{},"text","4.0"],["fn",{},"text","PINHAIS TELECOM COMERCIO E SERVI?OS LTDA"],["adr",{"label":"Av. das Na??es Unidas 11541 (7? andar)\nPinhais, PR 04578-000\nBR","type":"work"},"text",["","","Av. das Na??es Unidas 11541 (7? andar)","Pinhais","PR","04578-000","BR"]],["email",{"type":"work"},"text","PTL8@NUMERACAO.REGISTRO.BR"],["tel",{"type":"work"},"text","55 41 55093511 ()"],["kind",{},"text","individual"],["lang",{"pref":"1"},"language-tag","EN"]] ],
    "events" : [ {
      "eventAction" : "registration",
      "eventDate" : "20130306",
      "eventActor" : null
    }, {
      "eventAction" : "last changed",
      "eventDate" : "20130308",
      "eventActor" : "PTL8"
    } ],
    "entities" : [ ],
    "handle" : "PTL8"
  } ],
  "type" : null,
  "handle" : "263055-LACNIC",
  "country" : "BR"
}