{
  "startAutnum" : 53103,
  "endAutnum" : 53103,
  "status" : [ "allocated" ],
  "remarks" : [ ],
  "links" : [ {
    "rel" : "self",
    "href" : "http://rdap.labs.lacnic.net/autnum/53103",
    "value" : "http://rdap.labs.lacnic.net/autnum/53103"
  } ],
  "events" : [ {
    "eventAction" : "registration",
    "eventDate" : "20091127",
    "eventActor" : null
  }, {
    "eventAction" : "last changed",
    "eventDate" : "20130306",
    "eventActor" : "GTG3"
  } ],
  "entities" : [ {
    "roles" : [ "registrant" ],
    "remarks" : [ ],
    "links" : [ {
      "rel" : "self",
      "href" : "http://rdap.labs.lacnic.net/entity/BR-GPAA1-LACNIC",
      "value" : "http://rdap.labs.lacnic.net/entity/BR-GPAA1-LACNIC"
    } ],
    "vcardArray" : ["vcard",[["version",{},"text","4.0"],["fn",{},"text","Grupo T?tico Administrativo GsurfNET"],["adr",{"label":"Av. das Na??es Unidas 11541 (7? andar)\nGaropaba, SC 04578-000\nBR","type":"work"},"text",["","","Av. das Na??es Unidas 11541 (7? andar)","Garopaba","SC","04578-000","BR"]],["email",{"type":"work"},"text","GTG3@NUMERACAO.REGISTRO.BR"],["tel",{"type":"work"},"text","55 48 55093511 ()"],["org",{},"text",["GAROPABASURF PROVEDOR DE ACESSO A REDE DE TEL LTDA"]],["kind",{},"text","individual"]] ],
    "events" : [ {
      "eventAction" : "registration",
      "eventDate" : "20130306",
      "eventActor" : null
    }, {
      "eventAction" : "last changed",
      "eventDate" : "20130308",
      "eventActor" : "GTG3"
    } ],
    "entities" : [ {
      "roles" : [ "administrative" ],
      "remarks" : [ ],
      "links" : [ {
        "rel" : "self",
        "href" : "http://rdap.labs.lacnic.net/entity/GTG3",
        "value" : "http://rdap.labs.lacnic.net/entity/GTG3"
      } ],
      "vcardArray" : ["vcard",[["version",{},"text","4.0"],["fn",{},"text","Grupo T?tico Administrativo GsurfNET"],["adr",{"label":"Av. das Na??es Unidas 11541 (7? andar)\nGaropaba, SC 04578-000\nBR","type":"work"},"text",["","","Av. das Na??es Unidas 11541 (7? andar)","Garopaba","SC","04578-000","BR"]],["email",{"type":"work"},"text","GTG3@NUMERACAO.REGISTRO.BR"],["tel",{"type":"work"},"text","55 48 55093511 ()"],["kind",{},"text","individual"],["lang",{"pref":"1"},"language-tag","EN"]] ],
      "events" : [ {
        "eventAction" : "registration",
        "eventDate" : "20130306",
        "eventActor" : null
      }, {
        "eventAction" : "last changed",
        "eventDate" : "20130308",
        "eventActor" : "GTG3"
      } ],
      "entities" : [ ],
      "handle" : "GTG3"
    } ],
    "handle" : "BR-GPAA1-LACNIC"
  }, {
    "roles" : [ "tech" ],
    "remarks" : [ ],
    "links" : [ {
      "rel" : "self",
      "href" : "http://rdap.labs.lacnic.net/entity/GTG3",
      "value" : "http://rdap.labs.lacnic.net/entity/GTG3"
    } ],
    "vcardArray" : ["vcard",[["version",{},"text","4.0"],["fn",{},"text","Grupo T?tico Administrativo GsurfNET"],["adr",{"label":"Av. das Na??es Unidas 11541 (7? andar)\nGaropaba, SC 04578-000\nBR","type":"work"},"text",["","","Av. das Na??es Unidas 11541 (7? andar)","Garopaba","SC","04578-000","BR"]],["email",{"type":"work"},"text","GTG3@NUMERACAO.REGISTRO.BR"],["tel",{"type":"work"},"text","55 48 55093511 ()"],["kind",{},"text","individual"],["lang",{"pref":"1"},"language-tag","EN"]] ],
    "events" : [ {
      "eventAction" : "registration",
      "eventDate" : "20130306",
      "eventActor" : null
    }, {
      "eventAction" : "last changed",
      "eventDate" : "20130308",
      "eventActor" : "GTG3"
    } ],
    "entities" : [ ],
    "handle" : "GTG3"
  }, {
    "roles" : [ "abuse" ],
    "remarks" : [ ],
    "links" : [ {
      "rel" : "self",
      "href" : "http://rdap.labs.lacnic.net/entity/GTG3",
      "value" : "http://rdap.labs.lacnic.net/entity/GTG3"
    } ],
    "vcardArray" : ["vcard",[["version",{},"text","4.0"],["fn",{},"text","Grupo T?tico Administrativo GsurfNET"],["adr",{"label":"Av. das Na??es Unidas 11541 (7? andar)\nGaropaba, SC 04578-000\nBR","type":"work"},"text",["","","Av. das Na??es Unidas 11541 (7? andar)","Garopaba","SC","04578-000","BR"]],["email",{"type":"work"},"text","GTG3@NUMERACAO.REGISTRO.BR"],["tel",{"type":"work"},"text","55 48 55093511 ()"],["kind",{},"text","individual"],["lang",{"pref":"1"},"language-tag","EN"]] ],
    "events" : [ {
      "eventAction" : "registration",
      "eventDate" : "20130306",
      "eventActor" : null
    }, {
      "eventAction" : "last changed",
      "eventDate" : "20130308",
      "eventActor" : "GTG3"
    } ],
    "entities" : [ ],
    "handle" : "GTG3"
  } ],
  "type" : null,
  "handle" : "53103-LACNIC",
  "country" : "BR"
}