{"asn":{"@xmlns":{"ns3":"http:\/\/www.arin.net\/whoisrws\/netref\/v2","ns2":"http:\/\/www.arin.net\/whoisrws\/rdns\/v1","$":"http:\/\/www.arin.net\/whoisrws\/core\/v1"},"@termsOfUse":"https:\/\/www.arin.net\/whois_tou.html","@inaccuracyReportUrl":"http:\/\/www.arin.net\/public\/whoisinaccuracy\/index.xhtml","registrationDate":{"$":"1987-01-23T00:00:00-05:00"},"ref":{"$":"http:\/\/whois.arin.net\/rest\/asn\/AS95"},"endAsNumber":{"$":"95"},"handle":{"$":"AS95"},"name":{"$":"DNIC-AS-00095"},"orgRef":{"@name":"DoD Network Information Center","@handle":"DNIC","$":"http:\/\/whois.arin.net\/rest\/org\/DNIC"},"startAsNumber":{"$":"95"},"updateDate":{"$":"2012-07-23T15:00:44-04:00"}}}